[
  {
    "course": "Blockchain Technology",
    "url": "blockchain",
    "description": "This course encompasses Blockchain Technology. Whether you are an absolute beginner or a professional, this course has something for you. Further information on the level of each course can be found below. Select your course and get educated on this super exciting topic!",
    "quiz": "QmXsnYGKXxrAKiZKQ6AHtiwJq19xQoav9ea5Fs6tmB7xtU",
    "quickLinks": [
      {
        "linkTitle": "Course information",
        "linkUrl": "https://docs.google.com/document/d/1Baby83z9EVOOxBef1sgTUQ9YXwGKpBod/edit"
      },
      {
        "linkTitle": "See schedule",
        "linkUrl": "https://docs.google.com/spreadsheets/d/1ykzSXWojCVEou3GSyweuMS1lg3nvlpOZL9Kq8OzpnHA/edit?usp=sharing"
      }
    ],
    "content": [
      {
        "title": "Blockchain level 1",
        "videoInfo": "QmT9vZ78djiZrQixsfTjWqDgbMZs7m6crrUj1hqgYLnY2E",
        "data": "QmTPZUavGLVspuoPHHwJwxbsrkt6V3bJPL7Q2ikLUNTS1c",
        "subtitle": "Economics"
      },
      {
        "title": "Blockchain level 2",
        "videoInfo": "QmVS36BRyF68YNS46dQ9xM3MLRnD2vgM84iV8w1mspyAyJ",
        "data": "QmXa6GF9MLBtpeE1dGpwm3GWvMbFYNh5whaaZuYjvyzErP",
        "subtitle": "Distributed Ledger Technology"
      },
      {
        "title": "Blockchain level 3",
        "videoInfo": "QmPMMaPkekVioCSPHmERYpJ7EdcUZGdSUNm5yGJEmouRji",
        "data": "QmNyDU4KauqoXQSHQphcbP8M6rsmaZcP5JEssRSULuw7Eg",
        "subtitle": "Disruptive innovation"
      }
    ],
    "earn": [
      {
        "title": "Sidejobs and internships",
        "linkUrl": "/link"
      },
      {
        "title": "Microchallenges",
        "linkUrl": "/link"
      },
      {
        "title": "Partnergrants",
        "linkUrl": "/link"
      },
      {
        "title": "Ecosystem lectures",
        "linkUrl": "/link"
      },
      {
        "title": "Funding",
        "linkUrl": "/link"
      }
    ],
    "connect": [
      {
        "title": "Blackbirds",
        "linkUrl": "/link"
      },
      {
        "title": "Koios events",
        "linkUrl": "/link"
      },
      {
        "title": "Partner events",
        "linkUrl": "/link"
      },
      {
        "title": "Local communities",
        "linkUrl": "/link"
      }
    ],
    "team": [
      {
        "subtitle": "When you join Koios, you're immediately put in a room with 1000+ people active in Web3.",
        "p1": "This includes field experts, teachers, researchers, builders, gamers, designers, moon boys & girls, and artists. Many are talented individuals exploring what's next for our internet culture. \nHere are some examples of the most active community members in this world whom you'll be joining.",
        "p2": "",
        "members": [
          {
            "name": "Gerard Persoon",
            "imageUrl": "https://cdn.discordapp.com/avatars/525687122233917471/a5206ac46ce91d176a22b99ce947ef2d.png?size=256",
            "description": "Deep into the technical details of blockchains",
            "twitterLink": "https://twitter.com/gpersoon",
            "twitterHandle": "@gpersoon",
            "discordLink": "https://discord.com/users/525687122233917471",
            "discordHandle": "Gerard Persoon"
          },
          {
            "name": "Jamie Jansen",
            "imageUrl": "https://media-exp1.licdn.com/dms/image/C4D03AQFuxf2ASN9pyA/profile-displayphoto-shrink_200_200/0/1580551129552?e=1635379200&v=beta&t=bk-lrt4kbXck9N-zI1IwNM074aaVOCUWfCZKaVrX7S4",
            "description": "Gamified (digital) Education | DLT & DeFi Lecturer & Researcher",
            "twitterLink": "https://twitter.com/JamieJansen333",
            "twitterHandle": "@JamieJansen333",
            "discordLink": "https://discord.com/users/452760677418008617",
            "discordHandle": "Jamie.koios"
          },
          {
            "name": "Malva Ahmed",
            "imageUrl": "https://cdn.discordapp.com/avatars/801485039611150416/b091019dd6f35c6fe690480eb7992d53.png?size=256",
            "description": "2 years in developer relations in blockchain",
            "twitterLink": "https://twitter.com",
            "twitterHandle": "",
            "discordLink": "https://discord.com/users/801485039611150416",
            "discordHandle": "Malva.koios"
          },
          {
            "name": "Dennis IJlst",
            "imageUrl": "https://cdn.discordapp.com/avatars/801334609915805696/ae53525397d14f769f154c465ebded2a.png?size=256",
            "description": "2 years in developer relations in blockchain",
            "twitterLink": "https://twitter.com",
            "twitterHandle": "",
            "discordLink": "https://discord.com/users/801334609915805696",
            "discordHandle": "Dennis.koios"
          },
          {
            "name": "Jordi Jansen",
            "imageUrl": "https://cdn.discordapp.com/avatars/355982565288574977/cac5ed2fa3bf5bb2e36dd1f03a09189b.png?size=256",
            "description": "Researcher combining Education, DeFi and Web3",
            "twitterLink": "https://www.twitter.com/jordijansen101",
            "twitterHandle": "@jordijansen101",
            "discordLink": "https://discord.gg/jBjudugeBa",
            "discordHandle": "Jordi.koios"
          }
        ]
      }
    ]
  },
  {
    "course": "Trading Digital & Financial Assets",
    "url": "tdfa01",
    "description": "Learn everything about investing and trading in traditional and digital asset (crypto) markets. Everything from Fundamental to technical analysis to risk management and trading/investing psychology. From Amazon to Gold and from Bitcoin to Decentralized Finance (DeFi)",
    "quickLinks": [
      {
        "linkTitle": "Course information",
        "linkUrl": "https://docs.google.com/document/d/1LBIBqyxI-yzfgwOvGiZZQNl0NPesElWo/edit"
      },
      {
        "linkTitle": "Assignments",
        "linkUrl": "https://drive.google.com/drive/folders/1vwULXRufACWcpJ0DShsJQmVTxv6cP4ce"
      },
      {
        "linkTitle": "Join Discord",
        "linkUrl": "https://discord.com/invite/jBjudugeBa"
      },
      {
        "linkTitle": "See schedule",
        "linkUrl": "https://docs.google.com/spreadsheets/d/1zswX0eKrzXgdxUVGPWeDeZTfN7xKwtctU0ZPSVExg-Y/edit?usp=sharing"
      },
      {
        "linkTitle": "Kies op maat info",
        "linkUrl": "https://www.kiesopmaat.nl/modules/hhs/BFM/141244/"
      }
    ],
    "content": [
      {
        "title": "Trading Digital level 1",
        "videoInfo": "QmfKuBS7N3QqBHzkXq5PHNAobzr6auHzqURXF15Utp2i2V",
        "data": "QmRGWvHn3wksXEf2s8Cod3Kw9TWzDXb84MWAZEADPKwz3A"
      }
    ],
    "earn": [
      {
        "title": "Sidejobs and internships",
        "linkUrl": "/link"
      },
      {
        "title": "Microchallenges",
        "linkUrl": "/link"
      },
      {
        "title": "Partnergrants",
        "linkUrl": "/link"
      },
      {
        "title": "Ecosystem lectures",
        "linkUrl": "/link"
      },
      {
        "title": "Funding",
        "linkUrl": "/link"
      }
    ],
    "connect": [
      {
        "title": "Blackbirds",
        "linkUrl": "/link"
      },
      {
        "title": "Koios events",
        "linkUrl": "/link"
      },
      {
        "title": "Partner events",
        "linkUrl": "/link"
      },
      {
        "title": "Local communities",
        "linkUrl": "/link"
      }
    ],
    "team": [
      {
        "subtitle": "When you join Koios, you're immediately put in a room with 1000+ people active in Web3.",
        "p1": "This includes field experts, teachers, researchers, builders, gamers, designers, moon boys & girls, and artists. Many are talented individuals exploring what's next for our internet culture. \nHere are some examples of the most active community members in this world whom you'll be joining.",
        "p2": "",
        "members": [
          {
            "name": "Malva Ahmed",
            "imageUrl": "https://cdn.discordapp.com/avatars/801485039611150416/b091019dd6f35c6fe690480eb7992d53.png?size=256",
            "description": "Coordinator minor",
            "twitterLink": "https://twitter.com",
            "twitterHandle": "",
            "discordLink": "https://discord.com/users/801485039611150416",
            "discordHandle": "Malva.koios"
          },
          {
            "name": "Ricardo Eradus",
            "imageUrl": "https://media-exp1.licdn.com/dms/image/C5603AQG-ZrRkvfq5Pg/profile-displayphoto-shrink_200_200/0/1599399278857?e=1635379200&v=beta&t=QPxadx36MObXXc91ZAY2SgS3UduweB0Y70kDFb6kQm8",
            "description": "Co-initiator Koios & lecturer TDFA/FIT",
            "twitterLink": "https://twitter.com/tdfatweets",
            "twitterHandle": "@tdfatweets",
            "discordLink": "https://discord.com/users/758707515772239933",
            "discordHandle": "Ricardo.koios"
          },
          {
            "name": "Jordi Jansen",
            "imageUrl": "https://cdn.discordapp.com/avatars/355982565288574977/cac5ed2fa3bf5bb2e36dd1f03a09189b.png?size=256",
            "description": "Researcher combining Education, DeFi and Web3",
            "twitterLink": "https://www.twitter.com/jordijansen101",
            "twitterHandle": "@jordijansen101",
            "discordLink": "https://discord.com/users/355982565288574977",
            "discordHandle": "Jordi.koios"
          }
        ]
      }
    ]
  },
  {
    "course": "Data Science for Business Improvement",
    "url": "datascience01",
    "description": "In the minor, students experience the full cycle of a data project: identification of the information need, finding available data sources and improving the quality of that data. Next phase: tools like Python and statistical models help to do advanced analysis (applying Machine Learning algorithms) on the data and create visual reports with data driven recommendations. Legal and ethical aspects of data projects are also covered in the program.",
    "quickLinks": [
      {
        "linkTitle": "Course description",
        "linkUrl": "https://docs.google.com/document/d/17YAuGbQnCDL5knRzZpavB-LpP7frAIUV20iIw9Ik3qU/edit"
      },
      {
        "linkTitle": "Kies op maat",
        "linkUrl": "https://www.kiesopmaat.nl/modules/hhs/BFM/141245/"
      }
    ],
    "earn": [
      {
        "title": "Sidejobs and internships",
        "linkUrl": "/link"
      },
      {
        "title": "Microchallenges",
        "linkUrl": "/link"
      },
      {
        "title": "Partnergrants",
        "linkUrl": "/link"
      },
      {
        "title": "Ecosystem lectures",
        "linkUrl": "/link"
      },
      {
        "title": "Funding",
        "linkUrl": "/link"
      }
    ],
    "connect": [
      {
        "title": "Blackbirds",
        "linkUrl": "/link"
      },
      {
        "title": "Koios events",
        "linkUrl": "/link"
      },
      {
        "title": "Partner events",
        "linkUrl": "/link"
      },
      {
        "title": "Local communities",
        "linkUrl": "/link"
      }
    ]
  },
  {
    "course": "Programming Dapps",
    "url": "programmingdapps01",
    "description": "The course “Programming Dapps” teaches students to program distributed applications (DAPPS) for the public Ethereum blockchain.",
    "content": [
      {
        "title": "Programming Dapps level 1",
        "videoInfo": "QmadJkHttoKRR1ncAV8yMZFoyynwdWfqufcP7jofoMfVGr",
        "data":	"Qmd3NWeVNPRi5GUeyQMA3aZKSEZrEYofXXvgBhfAqL3E5c"
      }
    ],
    "earn": [
      {
        "title": "Sidejobs and internships",
        "linkUrl": "/link"
      },
      {
        "title": "Microchallenges",
        "linkUrl": "/link"
      },
      {
        "title": "Partnergrants",
        "linkUrl": "/link"
      },
      {
        "title": "Ecosystem lectures",
        "linkUrl": "/link"
      },
      {
        "title": "Funding",
        "linkUrl": "/link"
      }
    ],
    "connect": [
      {
        "title": "Blackbirds",
        "linkUrl": "/link"
      },
      {
        "title": "Koios events",
        "linkUrl": "/link"
      },
      {
        "title": "Partner events",
        "linkUrl": "/link"
      },
      {
        "title": "Local communities",
        "linkUrl": "/link"
      }
    ]
  }
]
